NtfyPy/Decorator.py
NtfyPy/Notification.py
NtfyPy/Settings.py
NtfyPy/__init__.py
NtfyPy/__main__.py
ntfypy-0.0.5.dist-info/METADATA
ntfypy-0.0.5.dist-info/WHEEL
ntfypy-0.0.5.dist-info/entry_points.txt
ntfypy-0.0.5.dist-info/licenses/LICENSE
ntfypy-0.0.5.dist-info/RECORD
