Metadata-Version: 2.4
Name: NtfyPy
Version: 0.0.5
Summary: A very small package that allows using Ntfy to send notifications
Project-URL: Homepage, https://github.com/Ilyass-Bougati/ntpy
Author-email: Ilyass Bougati <i.bougati12@gmail.com>
License-Expression: MIT
License-File: LICENSE
Classifier: Operating System :: OS Independent
Classifier: Programming Language :: Python :: 3
Requires-Python: >=3.9
Requires-Dist: pydantic-settings>=2.10.1
Requires-Dist: requests>=2.25.1
